reipresoplot/__init__.py
reipresoplot/generate_items_for_focus.py
reipresoplot/get_mpl_style_path.py
reipresoplot/plot_bar_graph.py
reipresoplot/plot_line_graph.py
reipresoplot/transform_to_2d_numpy.py
reipresoplot/use_rei_style_as_global_settings.py
reipresoplot/mplstyle/nakurei_bar_graph.mplstyle
reipresoplot/mplstyle/nakurei_line_graph.mplstyle
rei_preso_plot-0.1.0.dist-info/LICENSE
rei_preso_plot-0.1.0.dist-info/METADATA
rei_preso_plot-0.1.0.dist-info/WHEEL
rei_preso_plot-0.1.0.dist-info/top_level.txt
rei_preso_plot-0.1.0.dist-info/RECORD
