Metadata-Version: 2.1
Name: rei-preso-plot
Version: 0.1.0
Summary: Python package for drawing graphs for presentation materials with matplotlib.
Author-email: NakuRei <nakurei7901@gmail.com>
License: MIT License
Project-URL: Homepage, https://github.com/NakuRei/rei-preso-plot
Project-URL: Bug Tracker, https://github.com/NakuRei/rei-preso-plot/issues
Keywords: graph,plot,presentation,preso
Classifier: Programming Language :: Python :: 3
Classifier: License :: OSI Approved :: MIT License
Classifier: Operating System :: OS Independent
Requires-Python: >=3.7
License-File: LICENSE
Requires-Dist: matplotlib
